{
	"configurations" : 
	[
		{
			"abstractTargets" : 
			[
				{
					"directoryIndex" : 1,
					"id" : "stm32cubemx::@768a070a0fe75716b479",
					"jsonFile" : "target-stm32cubemx-Debug-13734a158fcf51789889.json",
					"name" : "stm32cubemx",
					"projectIndex" : 0
				}
			],
			"directories" : 
			[
				{
					"build" : ".",
					"childIndexes" : 
					[
						1
					],
					"jsonFile" : "directory-.-Debug-f040eec181a89de70dbe.json",
					"minimumCMakeVersion" : 
					{
						"string" : "3.22"
					},
					"projectIndex" : 0,
					"source" : ".",
					"targetIndexes" : 
					[
						3
					]
				},
				{
					"abstractTargetIndexes" : 
					[
						0
					],
					"build" : "cmake/stm32cubemx",
					"jsonFile" : "directory-cmake.stm32cubemx-Debug-720efe0a241989607e76.json",
					"minimumCMakeVersion" : 
					{
						"string" : "3.22"
					},
					"parentIndex" : 0,
					"projectIndex" : 0,
					"source" : "cmake/stm32cubemx",
					"targetIndexes" : 
					[
						0,
						1,
						2
					]
				}
			],
			"name" : "Debug",
			"projects" : 
			[
				{
					"abstractTargetIndexes" : 
					[
						0
					],
					"directoryIndexes" : 
					[
						0,
						1
					],
					"name" : "diankong_jie",
					"targetIndexes" : 
					[
						0,
						1,
						2,
						3
					]
				}
			],
			"targets" : 
			[
				{
					"directoryIndex" : 1,
					"id" : "FreeRTOS::@768a070a0fe75716b479",
					"jsonFile" : "target-FreeRTOS-Debug-b27e61377270e5c633fe.json",
					"name" : "FreeRTOS",
					"projectIndex" : 0
				},
				{
					"directoryIndex" : 1,
					"id" : "STM32_Drivers::@768a070a0fe75716b479",
					"jsonFile" : "target-STM32_Drivers-Debug-7367f401a0eb7fdb66a9.json",
					"name" : "STM32_Drivers",
					"projectIndex" : 0
				},
				{
					"directoryIndex" : 1,
					"id" : "USB_Device_Library::@768a070a0fe75716b479",
					"jsonFile" : "target-USB_Device_Library-Debug-47693ec2a909daf027a0.json",
					"name" : "USB_Device_Library",
					"projectIndex" : 0
				},
				{
					"directoryIndex" : 0,
					"id" : "diankong_jie::@6890427a1f51a3e7e1df",
					"jsonFile" : "target-diankong_jie-Debug-9180bf0356eb9bac62f4.json",
					"name" : "diankong_jie",
					"projectIndex" : 0
				}
			]
		}
	],
	"kind" : "codemodel",
	"paths" : 
	{
		"build" : "E:/RM/libxr_exe/diankong_jie/build/Debug",
		"source" : "E:/RM/libxr_exe/diankong_jie"
	},
	"version" : 
	{
		"major" : 2,
		"minor" : 10
	}
}
